<?xml version="1.0" ?>
<corpus xmlns:xsi="http://www.w3.org/2001/XMLSchema-instance"
 xsi:noNamespaceSchemaLocation="../../../xsds/darija_def.xsd">
  <entry>
    <indef>rajl</indef>
    <def>rrajl</def>
  </entry>
  <entry>
    <indef>klb</indef>
    <def>lklb</def>
  </entry>
  <entry>
    <indef>minjara</indef>
    <def>lminjara</def>
  </entry>
  <entry>
    <indef>SbbaT</indef>
    <def>SSbbaT</def>
  </entry>
  <entry>
    <indef>korsi</indef>
    <def>lkorsi</def>
  </entry>
  <entry>
    <indef>98wa</indef>
    <def>l98wa</def>
  </entry>
  <entry>
    <indef>insan</indef>
    <def>l2insan</def>
  </entry>
  <entry>
    <indef>oukla</indef>
    <def>l2oukla</def>
  </entry>
  <entry>
    <indef>a7lam</indef>
    <def>l2a7lam</def>
  </entry>
  <entry>
    <indef>srwal</indef>
    <def>ssrwal</def>
  </entry>
  <entry>
    <indef>Tbla</indef>
    <def>TTbla</def>
  </entry>
  <entry>
    <indef>kas</indef>
    <def>lkas</def>
  </entry>
  <entry>
    <indef>ma</indef>
    <def>lma</def>
  </entry>
  <entry>
    <indef>8wa</indef>
    <def>l8wa</def>
  </entry>
  <entry>
    <indef>9r3a</indef>
    <def>l9r3a</def>
  </entry>
  <entry>
    <indef>dar</indef>
    <def>ddar</def>
  </entry>
  <entry>
    <indef>bit</indef>
    <def>lbit</def>
  </entry>
  <entry>
    <indef>mdrasa</indef>
    <def>lmdrasa</def>
  </entry>
  <entry>
    <indef>tomobil</indef>
    <def>ttomobil</def>
  </entry>
  <entry>
    <indef>motor</indef>
    <def>lmotor</def>
  </entry>
  <entry>
    <indef>chffar</indef>
    <def>chchffar</def>
  </entry>
  <entry>
    <indef>chjra</indef>
    <def>chchjra</def>
  </entry>
  <entry>
    <indef>3imara</indef>
    <def>l3imara</def>
  </entry>
  <entry>
    <indef>partma</indef>
    <def>lpartma</def>
  </entry>
  <entry>
    <indef>jrda</indef>
    <def>jjrda</def>
  </entry>
  <entry>
    <indef>n3as</indef>
    <def>nn3as</def>
  </entry>
  <entry>
    <indef>wld</indef>
    <def>lwld</def>
  </entry>
  <entry>
    <indef>bnt</indef>
    <def>lbnt</def>
  </entry>
  <entry>
    <indef>pikala</indef>
    <def>lppikala</def>
  </entry>
  <entry>
    <indef>tobis</indef>
    <def>ttobis</def>
  </entry>
  <entry>
    <indef>chari3</indef>
    <def>chchari3</def>
  </entry>
  <entry>
    <indef>drb</indef>
    <def>ddrb</def>
  </entry>
  <entry>
    <indef>7ouma</indef>
    <def>l7ouma</def>
  </entry>
  <entry>
    <indef>drouj</indef>
    <def>ddrouj</def>
  </entry>
  <entry>
    <indef>ferrouj</indef>
    <def>lferrouj</def>
  </entry>
  <entry>
    <indef>nkhla</indef>
    <def>nnkhla</def>
  </entry>
  <entry>
    <indef>lougha</indef>
    <def>llougha</def>
  </entry>
  <entry>
    <indef>3am</indef>
    <def>l3am</def>
  </entry>
  <entry>
    <indef>fakhour</indef>
    <def>lfakhour</def>
  </entry>
  <entry>
    <indef>yom</indef>
    <def>lyom</def>
  </entry>
  <entry>
    <indef>namousia</indef>
    <def>nnamousia</def>
  </entry>
  <entry>
    <indef>Se8d</indef>
    <def>SSe8d</def>
  </entry>
  <entry>
    <indef>3aada</indef>
    <def>l3aada</def>
  </entry>
  <entry>
    <indef>ntikhabat</indef>
    <def>nntikhabat</def>
  </entry>
  <entry>
    <indef>brlaman</indef>
    <def>lbrlaman</def>
  </entry>
  <entry>
    <indef>malik</indef>
    <def>lmalik</def>
  </entry>
  <entry>
    <indef>wzir</indef>
    <def>lwzir</def>
  </entry>
  <entry>
    <indef>brlamani</indef>
    <def>lbrlamani</def>
  </entry>
  <entry>
    <indef>ktichaf</indef>
    <def>lktichaf</def>
  </entry>
  <entry>
    <indef>charika</indef>
    <def>chcharika</def>
  </entry>
  <entry>
    <indef>mo9awala</indef>
    <def>lmo9awala</def>
  </entry>
  <entry>
    <indef>3chir</indef>
    <def>l3chir</def>
  </entry>
  <entry>
    <indef>sou9</indef>
    <def>ssou9</def>
  </entry>
  <entry>
    <indef>marchi</indef>
    <def>lmarchi</def>
  </entry>
  <entry>
    <indef>nhar</indef>
    <def>nnhar</def>
  </entry>
  <entry>
    <indef>7arb</indef>
    <def>l7arb</def>
  </entry>
  <entry>
    <indef>7bs</indef>
    <def>l7bs</def>
  </entry>
  <entry>
    <indef>7bbas</indef>
    <def>l7bbas</def>
  </entry>
  <entry>
    <indef>jarima</indef>
    <def>ljarima</def>
  </entry>
  <entry>
    <indef>frdi</indef>
    <def>lfrdi</def>
  </entry>
  <entry>
    <indef>mk7la</indef>
    <def>lmk7la</def>
  </entry>
  <entry>
    <indef>9rtas</indef>
    <def>l9rtas</def>
  </entry>
  <entry>
    <indef>mous</indef>
    <def>lmous</def>
  </entry>
  <entry>
    <indef>m3il9a</indef>
    <def>lm3il9a</def>
  </entry>
  <entry>
    <indef>3ach9a</indef>
    <def>l3ach9a</def>
  </entry>
  <entry>
    <indef>frchiTa</indef>
    <def>lfrchiTa</def>
  </entry>
  <entry>
    <indef>biro</indef>
    <def>lbiro</def>
  </entry>
  <entry>
    <indef>chrjm</indef>
    <def>chchrjm</def>
  </entry>
  <entry>
    <indef>jar</indef>
    <def>jjar</def>
  </entry>
  <entry>
    <indef>jiran</indef>
    <def>jjiran</def>
  </entry>
  <entry>
    <indef>fya9</indef>
    <def>lfya9</def>
  </entry>
  <entry>
    <indef>Sda3</indef>
    <def>SSda3</def>
  </entry>
  <entry>
    <indef>tanffos</indef>
    <def>ttanffos</def>
  </entry>
  <entry>
    <indef>3oman</indef>
    <def>l3oman</def>
  </entry>
  <entry>
    <indef>7araka</indef>
    <def>l7araka</def>
  </entry>
  <entry>
    <indef>wo9ouf</indef>
    <def>lwo9ouf</def>
  </entry>
  <entry>
    <indef>t7m7ima</indef>
    <def>ttm7ima</def>
  </entry>
  <entry>
    <indef>7mmam</indef>
    <def>l7mmam</def>
  </entry>
  <entry>
    <indef>kouzina</indef>
    <def>lkouzina</def>
  </entry>
  <entry>
    <indef>Twalit</indef>
    <def>TTwalit</def>
  </entry>
  <entry>
    <indef>trikko</indef>
    <def>ttrikko</def>
  </entry>
  <entry>
    <indef>nDadr</indef>
    <def>nnDadr</def>
  </entry>
  <entry>
    <indef>3amalia</indef>
    <def>l3amalia</def>
  </entry>
  <entry>
    <indef>3amaliat</indef>
    <def>l3amaliat</def>
  </entry>
  <entry>
    <indef>Sa7afa</indef>
    <def>SSa7afa</def>
  </entry>
  <entry>
    <indef>mSdar</indef>
    <def>lmSdar</def>
  </entry>
  <entry>
    <indef>mnb3</indef>
    <def>lmnb3</def>
  </entry>
  <entry>
    <indef>3adawa</indef>
    <def>l3adawa</def>
  </entry>
  <entry>
    <indef>3onf</indef>
    <def>l3onf</def>
  </entry>
  <entry>
    <indef>mamlaka</indef>
    <def>lmamlaka</def>
  </entry>
  <entry>
    <indef>jomhoria</indef>
    <def>ljomhoria</def>
  </entry>
  <entry>
    <indef>jm8or</indef>
    <def>ljm8or</def>
  </entry>
  <entry>
    <indef>mowatin</indef>
    <def>lmowatin</def>
  </entry>
  <entry>
    <indef>tsrkila</indef>
    <def>ttsrkila</def>
  </entry>
  <entry>
    <indef>mosta9ill</indef>
    <def>lmosta9ill</def>
  </entry>
  <entry>
    <indef>3skr</indef>
    <def>l3skr</def>
  </entry>
  <entry>
    <indef>3arabia</indef>
    <def>l3arabia</def>
  </entry>
  <entry>
    <indef>ni9ach</indef>
    <def>nni9ach</def>
  </entry>
  <entry>
    <indef>mzian</indef>
    <def>lmzian</def>
  </entry>
  <entry>
    <indef>Tri9</indef>
    <def>TTri9</def>
  </entry>
  <entry>
    <indef>moSala7a</indef>
    <def>lmoSala7a</def>
  </entry>
  <entry>
    <indef>rafD</indef>
    <def>rrafD</def>
  </entry>
  <entry>
    <indef>khibra</indef>
    <def>lkhibra</def>
  </entry>
  <entry>
    <indef>ljna</indef>
    <def>lljna</def>
  </entry>
  <entry>
    <indef>dawla</indef>
    <def>ddawla</def>
  </entry>
  <entry>
    <indef>7o9o9</indef>
    <def>l7o9o9</def>
  </entry>
  <entry>
    <indef>7e99</indef>
    <def>l7e99</def>
  </entry>
  <entry>
    <indef>9owwa</indef>
    <def>l9owwa</def>
  </entry>
  <entry>
    <indef>Tbsil</indef>
    <def>TTbsil</def>
  </entry>
  <entry>
    <indef>mma3n</indef>
    <def>lmma3n</def>
  </entry>
  <entry>
    <indef>clim</indef>
    <def>laclim</def>
  </entry>
  <entry>
    <indef>mochkil</indef>
    <def>lmochkil</def>
  </entry>
  <entry>
    <indef>tsalim</indef>
    <def>ttsalim</def>
  </entry>
  <entry>
    <indef>3afia</indef>
    <def>l3afia</def>
  </entry>
  <entry>
    <indef>l8ja</indef>
    <def>ll8ja</def>
  </entry>
  <entry>
    <indef>ksida</indef>
    <def>lksida</def>
  </entry>
  <entry>
    <indef>Tyyara</indef>
    <def>TTyyara</def>
  </entry>
  <entry>
    <indef>faDa2i</indef>
    <def>lfaDa2i</def>
  </entry>
  <entry>
    <indef>moghamara</indef>
    <def>lmoghamara</def>
  </entry>
</corpus>
